{
  "metadata": {
    "region": "19102",
    "cuisine": "American (New)",
    "last_updated": "2025-07-28T21:36:13.026078",
    "data_sources": [
      "task1",
      "task2",
      "task3",
      "task4",
      "task5",
      "task6"
    ],
    "restaurant_count": 5,
    "data_quality": "region_specific"
  },
  "market_saturation": {
    "saturation_level": "medium",
    "restaurant_density": 5,
    "market_concentration": "medium",
    "entry_difficulty": "moderate",
    "average_rating": 3.2,
    "total_reviews": 1635,
    "market_analysis": "Region has 5 restaurants with 3.2 avg rating"
  },
  "key_competitors": [
    {
      "name": "R2L",
      "business_id": "9gObo5ltOMo6UgsaXaHPWA",
      "market_position": "mid-range",
      "threat_level": "medium",
      "rating": 3.5,
      "stars": 3.5,
      "review_count": 787,
      "competitor_score": 0.65,
      "address": "50 S 16th St, Fl 37",
      "city": "Philadelphia",
      "state": "PA",
      "key_strengths": "established customer base",
      "key_weaknesses": "no reservations; no delivery service"
    },
    {
      "name": "Marathon",
      "business_id": "-ATiAtTikuGuqvaW2O6tNA",
      "market_position": "mid-range",
      "threat_level": "medium",
      "rating": 3.5,
      "stars": 3.5,
      "review_count": 593,
      "competitor_score": 0.65,
      "address": "121 S 16th St",
      "city": "Philadelphia",
      "state": "PA",
      "key_strengths": "established customer base",
      "key_weaknesses": "no reservations; no delivery service"
    },
    {
      "name": "Vesper Sporting Club - Center City",
      "business_id": "aNNCjIDnTxn3YXRa4SnzYA",
      "market_position": "mid-range",
      "threat_level": "medium",
      "rating": 3.5,
      "stars": 3.5,
      "review_count": 157,
      "competitor_score": 0.62,
      "address": "223 S Sydenham St",
      "city": "Philadelphia",
      "state": "PA",
      "key_strengths": "growing customer base",
      "key_weaknesses": "no reservations; no delivery service"
    },
    {
      "name": "Enzo's",
      "business_id": "BVe-jR0szZPC6o7r15jp4g",
      "market_position": "mid-range",
      "threat_level": "medium",
      "rating": 3.5,
      "stars": 3.5,
      "review_count": 9,
      "competitor_score": 0.53,
      "address": "120 S 15th St",
      "city": "Philadelphia",
      "state": "PA",
      "key_strengths": "established presence",
      "key_weaknesses": "limited customer feedback; no reservations; no delivery service"
    },
    {
      "name": "Applebee's Grill + Bar",
      "business_id": "lAni_2IBdJOUMGXYXSmU2g",
      "market_position": "budget",
      "threat_level": "low",
      "rating": 2.0,
      "stars": 2.0,
      "review_count": 89,
      "competitor_score": 0.35,
      "address": "215 S 15th St",
      "city": "Philadelphia",
      "state": "PA",
      "key_strengths": "established presence",
      "key_weaknesses": "customer satisfaction issues; no reservations; no delivery service"
    }
  ],
  "competitive_gaps": [
    {
      "gap_type": "delivery_service",
      "description": "Only 0/5 restaurants offer delivery",
      "opportunity_size": "medium"
    },
    {
      "gap_type": "reservation_system",
      "description": "Only 0/5 restaurants take reservations",
      "opportunity_size": "low"
    },
    {
      "gap_type": "quality_improvement",
      "description": "Average rating 3.2 below 4.0 threshold",
      "opportunity_size": "high"
    }
  ],
  "differentiation_opportunities": [
    {
      "opportunity": "Superior quality and service",
      "market_demand": "high",
      "implementation_difficulty": "medium",
      "competitive_advantage": "strong",
      "region_specific": true,
      "basis": "Current average rating 3.2 below 4.0"
    },
    {
      "opportunity": "Delivery service introduction",
      "market_demand": "high",
      "implementation_difficulty": "low",
      "competitive_advantage": "medium",
      "region_specific": true,
      "basis": "No current delivery options in region"
    }
  ],
  "success_benchmarks": {
    "top_performer_count": 2,
    "average_rating_leaders": 3.5,
    "average_reviews_leaders": 398,
    "regional_success_threshold": {
      "min_rating": 4.0,
      "min_reviews": 199
    },
    "success_factors_observed": [
      "improving_quality",
      "customer_engagement",
      "regional_adaptation"
    ]
  },
  "menu_optimization": {
    "status": "no_dish_data",
    "message": "No dish data available for American (New) cuisine"
  },
  "customer_insights": {
    "regional_customer_profile": {
      "sophistication_level": "price_conscious",
      "primary_preferences": [
        "value",
        "affordability",
        "convenience"
      ],
      "engagement_level": "high"
    },
    "market_indicators": {
      "total_regional_reviews": 1635,
      "average_satisfaction": 3.2,
      "restaurants_evaluated": 5
    },
    "regional_dining_culture": "active_reviewers_mixed_quality"
  },
  "risk_assessment": {
    "identified_risks": [
      {
        "risk_type": "high_competition",
        "level": "high",
        "details": "5 existing competitors"
      }
    ],
    "overall_risk_level": "low",
    "regional_context": "Analysis based on 5 regional competitors"
  },
  "actionable_recommendations": [
    {
      "category": "competitive_advantage",
      "recommendation": "Focus on superior quality - regional average is 3.2",
      "priority": "high",
      "timeline": "immediate",
      "expected_impact": "high",
      "region_specific": true
    },
    {
      "category": "service_differentiation",
      "recommendation": "Introduce delivery service - no regional competitors offer this",
      "priority": "high",
      "timeline": "launch",
      "expected_impact": "medium",
      "region_specific": true
    },
    {
      "category": "regional_adaptation",
      "recommendation": "Study successful patterns from 5 regional competitors",
      "priority": "medium",
      "timeline": "planning",
      "expected_impact": "medium",
      "region_specific": true
    }
  ]
}