{
  "metadata": {
    "region": "37201",
    "cuisine": "American (New)",
    "last_updated": "2025-07-28T21:36:13.751222",
    "data_sources": [
      "task1",
      "task2",
      "task3",
      "task4",
      "task5",
      "task6"
    ],
    "restaurant_count": 5,
    "data_quality": "region_specific"
  },
  "market_saturation": {
    "saturation_level": "medium",
    "restaurant_density": 5,
    "market_concentration": "medium",
    "entry_difficulty": "moderate",
    "average_rating": 3.6,
    "total_reviews": 1563,
    "market_analysis": "Region has 5 restaurants with 3.6 avg rating"
  },
  "key_competitors": [
    {
      "name": "Black Rabbit",
      "business_id": "8x7oJzbcOndkG7Mlo96eXA",
      "market_position": "premium",
      "threat_level": "high",
      "rating": 4.0,
      "stars": 4.0,
      "review_count": 176,
      "competitor_score": 0.71,
      "address": "218 3rd Ave N",
      "city": "Nashville",
      "state": "TN",
      "key_strengths": "strong customer satisfaction; growing customer base",
      "key_weaknesses": "no reservations; no delivery service"
    },
    {
      "name": "Jane’s Hideaway",
      "business_id": "Dp_yOU1VrnWDtntp2Kq1Kw",
      "market_position": "mid-range",
      "threat_level": "high",
      "rating": 4.5,
      "stars": 4.5,
      "review_count": 52,
      "competitor_score": 0.7,
      "address": "209 3rd Ave N",
      "city": "Nashville",
      "state": "TN",
      "key_strengths": "excellent customer satisfaction",
      "key_weaknesses": "no reservations; no delivery service"
    },
    {
      "name": "Ole Red",
      "business_id": "Sh5x88Ty9NGgMvLoIKxAiQ",
      "market_position": "mid-range",
      "threat_level": "medium",
      "rating": 3.5,
      "stars": 3.5,
      "review_count": 629,
      "competitor_score": 0.65,
      "address": "300 Broadway",
      "city": "Nashville",
      "state": "TN",
      "key_strengths": "established customer base",
      "key_weaknesses": "no reservations; no delivery service"
    },
    {
      "name": "Margaritaville - Nashville",
      "business_id": "kjhIbW8NKRvXmLDwz7lzhw",
      "market_position": "mid-range",
      "threat_level": "medium",
      "rating": 3.5,
      "stars": 3.5,
      "review_count": 580,
      "competitor_score": 0.65,
      "address": "322 Broadway",
      "city": "Nashville",
      "state": "TN",
      "key_strengths": "established customer base",
      "key_weaknesses": "no reservations; no delivery service"
    },
    {
      "name": "National Underground",
      "business_id": "RJPRi1pwocHNZr9ISz_P-A",
      "market_position": "budget",
      "threat_level": "low",
      "rating": 2.5,
      "stars": 2.5,
      "review_count": 126,
      "competitor_score": 0.45,
      "address": "105 Broadway",
      "city": "Nashville",
      "state": "TN",
      "key_strengths": "growing customer base",
      "key_weaknesses": "customer satisfaction issues; no reservations; no delivery service"
    }
  ],
  "competitive_gaps": [
    {
      "gap_type": "delivery_service",
      "description": "Only 0/5 restaurants offer delivery",
      "opportunity_size": "medium"
    },
    {
      "gap_type": "reservation_system",
      "description": "Only 0/5 restaurants take reservations",
      "opportunity_size": "low"
    },
    {
      "gap_type": "quality_improvement",
      "description": "Average rating 3.6 below 4.0 threshold",
      "opportunity_size": "high"
    }
  ],
  "differentiation_opportunities": [
    {
      "opportunity": "Superior quality and service",
      "market_demand": "high",
      "implementation_difficulty": "medium",
      "competitive_advantage": "strong",
      "region_specific": true,
      "basis": "Current average rating 3.6 below 4.0"
    },
    {
      "opportunity": "Delivery service introduction",
      "market_demand": "high",
      "implementation_difficulty": "low",
      "competitive_advantage": "medium",
      "region_specific": true,
      "basis": "No current delivery options in region"
    }
  ],
  "success_benchmarks": {
    "top_performer_count": 2,
    "average_rating_leaders": 4.25,
    "average_reviews_leaders": 114,
    "regional_success_threshold": {
      "min_rating": 4.0,
      "min_reviews": 57
    },
    "success_factors_observed": [
      "consistent_quality",
      "customer_engagement",
      "regional_adaptation"
    ]
  },
  "menu_optimization": {
    "status": "no_dish_data",
    "message": "No dish data available for American (New) cuisine"
  },
  "customer_insights": {
    "regional_customer_profile": {
      "sophistication_level": "medium",
      "primary_preferences": [
        "value",
        "quality",
        "convenience"
      ],
      "engagement_level": "high"
    },
    "market_indicators": {
      "total_regional_reviews": 1563,
      "average_satisfaction": 3.6,
      "restaurants_evaluated": 5
    },
    "regional_dining_culture": "active_reviewers_mixed_quality"
  },
  "risk_assessment": {
    "identified_risks": [
      {
        "risk_type": "high_competition",
        "level": "high",
        "details": "5 existing competitors"
      }
    ],
    "overall_risk_level": "low",
    "regional_context": "Analysis based on 5 regional competitors"
  },
  "actionable_recommendations": [
    {
      "category": "competitive_advantage",
      "recommendation": "Focus on superior quality - regional average is 3.6",
      "priority": "high",
      "timeline": "immediate",
      "expected_impact": "high",
      "region_specific": true
    },
    {
      "category": "service_differentiation",
      "recommendation": "Introduce delivery service - no regional competitors offer this",
      "priority": "high",
      "timeline": "launch",
      "expected_impact": "medium",
      "region_specific": true
    },
    {
      "category": "regional_adaptation",
      "recommendation": "Study successful patterns from 5 regional competitors",
      "priority": "medium",
      "timeline": "planning",
      "expected_impact": "medium",
      "region_specific": true
    }
  ]
}